localbin.py
localbin-0.0.3.dist-info/LICENSE
localbin-0.0.3.dist-info/METADATA
localbin-0.0.3.dist-info/WHEEL
localbin-0.0.3.dist-info/entry_points.txt
localbin-0.0.3.dist-info/top_level.txt
localbin-0.0.3.dist-info/RECORD
