Metadata-Version: 2.1
Name: localbin
Version: 0.0.3
Summary: Manages and installs scripts in /usr/local/bin
Home-page: https://ktpanda.org/software/localbin
Author: Katie Rust
Author-email: katie@ktpanda.org
License: MIT License
Classifier: Programming Language :: Python :: 3
Classifier: License :: OSI Approved :: MIT License
Classifier: Operating System :: OS Independent
Requires-Python: >=3.6
License-File: LICENSE
Requires-Dist: argcomplete (>=2.0.0)
